HarvestingKit-0.3.0.dist-info/METADATA
HarvestingKit-0.3.0.dist-info/RECORD
HarvestingKit-0.3.0.dist-info/entry_points.txt
HarvestingKit-0.3.0.dist-info/WHEEL
HarvestingKit-0.3.0.dist-info/DESCRIPTION.rst
HarvestingKit-0.3.0.dist-info/top_level.txt
HarvestingKit-0.3.0.dist-info/metadata.json
harvestingkit/springer_crawler.py
harvestingkit/app_utils.py
harvestingkit/utils.py
harvestingkit/__init__.py
harvestingkit/jats_package.py
harvestingkit/contrast_out.py
harvestingkit/elsevier_package.py
harvestingkit/aps_package.py
harvestingkit/harvestingkit_cli.py
harvestingkit/contrast_out_utils.py
harvestingkit/world_scientific_package.py
harvestingkit/springer_package.py
harvestingkit/minidom_utils.py
harvestingkit/scoap3utils.py
harvestingkit/nlm_utils.py
harvestingkit/configparser.py
harvestingkit/jats_utils.py
harvestingkit/ftp_utils.py
harvestingkit/hindawi_bibfilter.py
harvestingkit/oup_package.py
harvestingkit/edpsciences_package.py
harvestingkit/pos_package.py
harvestingkit/config.py
harvestingkit/tests/jats_utils_tests.py
harvestingkit/tests/__init__.py
harvestingkit/tests/utils_tests.py
harvestingkit/tests/world_scientific_package_tests.py
harvestingkit/tests/minidom_utils_tests.py
harvestingkit/tests/elsevier_package_tests.py
harvestingkit/tests/pos_package_tests.py
harvestingkit/tests/aps_package_tests.py
harvestingkit/tests/edpsciencespackage_tests.py
harvestingkit/tests/data/sample_edpsciences_record.xml
harvestingkit/tests/data/sample_aps_output.xml
harvestingkit/tests/data/sample_ws_erratum_output.xml
harvestingkit/tests/data/sample_elsevier_issue_output.xml
harvestingkit/tests/data/sample_elsevier_issue_input.xml
harvestingkit/tests/data/sample_consyn_record.xml
harvestingkit/tests/data/sample_aps_record.xml
harvestingkit/tests/data/sample_ws_erratum_record.xml
harvestingkit/tests/data/sample_edp_output.xml
harvestingkit/tests/data/sample_pos_record.xml
harvestingkit/tests/data/sample_ws_record.xml
harvestingkit/tests/data/sample_consyn_output.xml
harvestingkit/tests/data/sample_ws_output.xml
HarvestingKit-0.3.0.data/data/dtds/A++V2.4.zip
HarvestingKit-0.3.0.data/data/dtds/si510.zip
HarvestingKit-0.3.0.data/data/dtds/journal-publishing-dtd-2.3.zip
