Metadata-Version: 2.0
Name: HarvestingKit
Version: 0.3.0
Summary: Kit of tools to convert publisher XML (NLM/JATS) to MARCXML.
Home-page: https://github.com/inspirehep/harvesting-kit
Author: INSPIRE-HEP collaboration
Author-email: admin@inspirehep.net
License: GPLv2
Platform: UNKNOWN
Classifier: Development Status :: 4 - Beta
Classifier: Intended Audience :: Developers
Classifier: Topic :: Utilities
Classifier: Topic :: Text Processing
Classifier: Topic :: Text Processing :: Markup :: XML
Classifier: License :: OSI Approved :: GNU General Public License v2 (GPLv2)
Classifier: Programming Language :: Python :: 2
Classifier: Programming Language :: Python :: 2.7
Requires-Dist: beautifulsoup4 (==4.3.2)
Requires-Dist: Unidecode (==0.04.14)
Requires-Dist: argcomplete (==0.8.0)
Requires-Dist: httpretty (==0.8.3)
Requires-Dist: lxml (>=3.3)
Requires-Dist: requests (==2.2.0)
